[
    {
        "date": "2026-05-01 15:30:00",
        "action": "BUY",
        "ticker": "INTC",
        "price": 40.0,
        "quantity": 500.0,
        "realized_pnl": 0.0,
        "reason": "Perfect Storm setup detected"
    },
    {
        "date": "2026-06-15 15:30:00",
        "action": "BUY",
        "ticker": "PLTR",
        "price": 20.0,
        "quantity": 1000.0,
        "realized_pnl": 0.0,
        "reason": "Strong RS and Volume breakout"
    },
    {
        "date": "2026-07-01 15:30:00",
        "action": "BUY",
        "ticker": "MU",
        "price": 100.0,
        "quantity": 200.0,
        "realized_pnl": 0.0,
        "reason": "Earnings acceleration"
    },
    {
        "date": "2026-07-04 15:30:00",
        "action": "SELL",
        "ticker": "AAPL",
        "price": 150.0,
        "quantity": 133.33,
        "realized_pnl": 2000.0,
        "reason": "50div Overheat (82%)"
    }
]
