[
    {
        "date": "2026-07-06 16:58:46",
        "action": "BUY",
        "ticker": "SXI",
        "price": 327.8699951171875,
        "quantity": 60.999787409188166,
        "realized_pnl": 0.0,
        "reason": ""
    },
    {
        "date": "2026-07-06 16:58:46",
        "action": "BUY",
        "ticker": "APH",
        "price": 164.58999633789062,
        "quantity": 121.51406795672767,
        "realized_pnl": 0.0,
        "reason": ""
    },
    {
        "date": "2026-07-06 16:58:46",
        "action": "BUY",
        "ticker": "UCTT",
        "price": 106.4800033569336,
        "quantity": 187.82869430382743,
        "realized_pnl": 0.0,
        "reason": ""
    },
    {
        "date": "2026-07-07 12:44:29",
        "action": "BUY",
        "ticker": "MIDD",
        "price": 179.1999969482422,
        "quantity": 111.60714475780121,
        "realized_pnl": 0.0,
        "reason": ""
    }
]